scrobbify.py
setup.py
scrobbify.egg-info/PKG-INFO
scrobbify.egg-info/SOURCES.txt
scrobbify.egg-info/dependency_links.txt
scrobbify.egg-info/requires.txt
scrobbify.egg-info/top_level.txt
