Metadata-Version: 1.0
Name: scrobbify
Version: 0.1
Summary: Real-time 'now playing notifications' for Spotify
Home-page: http://github.com/swinton/scrobbify
Author: Steve Winton
Author-email: stevewinton@gmail.com
License: GPL
Keywords: spotify desktop
Platform: UNKNOWN
Classifier: Development Status :: 3 - Alpha
Classifier: Intended Audience :: Developers
Classifier: License :: Free For Home Use
Classifier: Natural Language :: English
Classifier: Programming Language :: Python
Classifier: Programming Language :: Python :: 2.5
Classifier: Topic :: Desktop Environment
